{
  "PrimaryBusiness": {
    "Relationship": "Director",
    "IsPrimary": true,
    "IsExisting": false,
    "CID": "5502621776631",
    "CRN": "55026217766316",
    "IsProfileLockedOut": null,
    "BusinessId": "dec244d4-9aac-4284-a7be-1686edeaaa82",
    "BusinessClassificationCode": "RMA",
    "BusinessClassification": "Registered Migration Agent",
    "BusinessType": "Company",
    "EntityName": "PRJB MARKETING PTY. LTD.",
    "Name": "PR MIGRATION SERVICES",
    "ABN": "83080947995",
    "Address": {
      "Country": "Australia",
      "AddressLine1": " Unit 3,",
      "AddressLine2": "28 Carrarra Street",
      "AddressLine3": null,
      "State": "QLD",
      "OtherState": null,
      "Suburb": "MOUNT GRAVATT EAST",
      "OtherSuburb": null,
      "PostCode": "4122",
      "OtherPostCode": null,
      "Latitude": -27.52421,
      "Longitude": 153.08155,
      "FullAddress": " Unit 3,\r\n28 Carrarra Street\r\nMOUNT GRAVATT EAST QLD 4122\r\nAustralia"
    },
    "PostalAddress": {
      "Country": null,
      "AddressLine1": null,
      "AddressLine2": null,
      "AddressLine3": null,
      "State": null,
      "OtherState": null,
      "Suburb": null,
      "OtherSuburb": null,
      "PostCode": null,
      "OtherPostCode": null,
      "Latitude": null,
      "Longitude": null,
      "FullAddress": ""
    },
    "Contact": {
      "Phone": {
        "CountryCode": "61",
        "AreaCode": "4",
        "Number": "14323257",
        "FullNumber": "61 4 14323257"
      },
      "Phone2": {
        "CountryCode": null,
        "AreaCode": null,
        "Number": null,
        "FullNumber": null
      },
      "Phone3": {
        "CountryCode": null,
        "AreaCode": null,
        "Number": null,
        "FullNumber": null
      },
      "Fax": {
        "CountryCode": "61",
        "AreaCode": "7",
        "Number": "33492839",
        "FullNumber": "61 7 33492839"
      },
      "EmailAddress1": null,
      "EmailAddress2": null
    },
    "WebsiteUrl": null,
    "IsBusinessNameSameAsOwner": null,
    "IsBusinessNameRegistered": null,
    "HasHoldingCharge": null,
    "HasChangesInName": null,
    "ChangesInNameDetail": null,
    "ConnectedAgents": [],
    "HasEmployees": null,
    "HavingEmployeesDetail": null,
    "PrimaryContactId": null,
    "VerifiedDocuments": null,
    "OptionalDocuments": [],
    "OptionalExpiringDocuments": []
  },
  "SecondaryBusinesses": [],
  "DisplayBusiness": {
    "Relationship": "Director",
    "IsPrimary": true,
    "IsExisting": false,
    "CID": "5502621776631",
    "CRN": "55026217766316",
    "IsProfileLockedOut": null,
    "BusinessId": "dec244d4-9aac-4284-a7be-1686edeaaa82",
    "BusinessClassificationCode": "RMA",
    "BusinessClassification": "Registered Migration Agent",
    "BusinessType": "Company",
    "EntityName": "PRJB MARKETING PTY. LTD.",
    "Name": "PR MIGRATION SERVICES",
    "ABN": "83080947995",
    "Address": {
      "Country": "Australia",
      "AddressLine1": " Unit 3,",
      "AddressLine2": "28 Carrarra Street",
      "AddressLine3": null,
      "State": "QLD",
      "OtherState": null,
      "Suburb": "MOUNT GRAVATT EAST",
      "OtherSuburb": null,
      "PostCode": "4122",
      "OtherPostCode": null,
      "Latitude": -27.52421,
      "Longitude": 153.08155,
      "FullAddress": " Unit 3,\r\n28 Carrarra Street\r\nMOUNT GRAVATT EAST QLD 4122\r\nAustralia"
    },
    "PostalAddress": {
      "Country": null,
      "AddressLine1": null,
      "AddressLine2": null,
      "AddressLine3": null,
      "State": null,
      "OtherState": null,
      "Suburb": null,
      "OtherSuburb": null,
      "PostCode": null,
      "OtherPostCode": null,
      "Latitude": null,
      "Longitude": null,
      "FullAddress": ""
    },
    "Contact": {
      "Phone": {
        "CountryCode": "61",
        "AreaCode": "4",
        "Number": "14323257",
        "FullNumber": "61 4 14323257"
      },
      "Phone2": {
        "CountryCode": null,
        "AreaCode": null,
        "Number": null,
        "FullNumber": null
      },
      "Phone3": {
        "CountryCode": null,
        "AreaCode": null,
        "Number": null,
        "FullNumber": null
      },
      "Fax": {
        "CountryCode": "61",
        "AreaCode": "7",
        "Number": "33492839",
        "FullNumber": "61 7 33492839"
      },
      "EmailAddress1": null,
      "EmailAddress2": null
    },
    "WebsiteUrl": null,
    "IsBusinessNameSameAsOwner": null,
    "IsBusinessNameRegistered": null,
    "HasHoldingCharge": null,
    "HasChangesInName": null,
    "ChangesInNameDetail": null,
    "ConnectedAgents": [],
    "HasEmployees": null,
    "HavingEmployeesDetail": null,
    "PrimaryContactId": null,
    "VerifiedDocuments": null,
    "OptionalDocuments": [],
    "OptionalExpiringDocuments": []
  },
  "Name": {
    "Salutation": "Mr",
    "FirstName": "Peter",
    "SecondName": "Ying-Wah",
    "FamilyName": "Chong",
    "PostNominal": null,
    "FullName": "Mr Peter Ying-Wah Chong",
    "GivenName": "Peter Ying-Wah"
  },
  "MARN": "0427207",
  "IsNoFee": false,
  "ContactId": "cdc8800b-a152-e311-9402-005056ab0eca",
  "CitizenshipCountries": [
    "Australia",
    "Malaysia"
  ],
  "OtherNames": [],
  "Aliases": [],
  "ApplicantReferenceID": null,
  "DisplayPublicationDate": "",
  "CurrentSanctionOutcome": null,
  "CurrentSanctionOutcome2": null,
  "SanctionedDate": null,
  "DisplaySanctionedDate": "",
  "DisplayCeasedDate": "01 Jan 0001"
}
