{
  "PrimaryBusiness": {
    "Relationship": "Director",
    "IsPrimary": true,
    "IsExisting": false,
    "CID": "6665976937287",
    "CRN": "66659769372873",
    "IsProfileLockedOut": null,
    "BusinessId": "d6640aca-9852-e311-9402-005056ab0eca",
    "BusinessClassificationCode": "RMA",
    "BusinessClassification": "Registered Migration Agent",
    "BusinessType": "Company",
    "EntityName": "SINCERITY AUSTRALIA BUSINESS & MIGRATION PTY. LTD.",
    "Name": "SINCERITY AUSTRALIA BUSINESS & MIGRATION PTY. LTD.",
    "ABN": "27139689786",
    "Address": {
      "Country": "Australia",
      "AddressLine1": "Level 9,",
      "AddressLine2": "167 Queen Street",
      "AddressLine3": null,
      "State": "VIC",
      "OtherState": null,
      "Suburb": "MELBOURNE",
      "OtherSuburb": null,
      "PostCode": "3000",
      "OtherPostCode": null,
      "Latitude": -37.8146236,
      "Longitude": 144.9604244,
      "FullAddress": "Level 9,\r\n167 Queen Street\r\nMELBOURNE VIC 3000\r\nAustralia"
    },
    "PostalAddress": {
      "Country": null,
      "AddressLine1": null,
      "AddressLine2": null,
      "AddressLine3": null,
      "State": null,
      "OtherState": null,
      "Suburb": "MELBOURNE",
      "OtherSuburb": null,
      "PostCode": null,
      "OtherPostCode": null,
      "Latitude": null,
      "Longitude": null,
      "FullAddress": "MELBOURNE"
    },
    "Contact": {
      "Phone": {
        "CountryCode": "61",
        "AreaCode": "1300",
        "Number": "737556",
        "FullNumber": "61 1300 737556"
      },
      "Phone2": {
        "CountryCode": null,
        "AreaCode": null,
        "Number": null,
        "FullNumber": null
      },
      "Phone3": {
        "CountryCode": null,
        "AreaCode": null,
        "Number": null,
        "FullNumber": null
      },
      "Fax": {
        "CountryCode": "61",
        "AreaCode": "3",
        "Number": "96428462",
        "FullNumber": "61 3 96428462"
      },
      "EmailAddress1": null,
      "EmailAddress2": null
    },
    "WebsiteUrl": null,
    "IsBusinessNameSameAsOwner": null,
    "IsBusinessNameRegistered": null,
    "HasHoldingCharge": null,
    "HasChangesInName": null,
    "ChangesInNameDetail": null,
    "ConnectedAgents": [],
    "HasEmployees": null,
    "HavingEmployeesDetail": null,
    "PrimaryContactId": null,
    "VerifiedDocuments": null,
    "OptionalDocuments": [],
    "OptionalExpiringDocuments": []
  },
  "SecondaryBusinesses": [],
  "DisplayBusiness": {
    "Relationship": "Director",
    "IsPrimary": true,
    "IsExisting": false,
    "CID": "6665976937287",
    "CRN": "66659769372873",
    "IsProfileLockedOut": null,
    "BusinessId": "d6640aca-9852-e311-9402-005056ab0eca",
    "BusinessClassificationCode": "RMA",
    "BusinessClassification": "Registered Migration Agent",
    "BusinessType": "Company",
    "EntityName": "SINCERITY AUSTRALIA BUSINESS & MIGRATION PTY. LTD.",
    "Name": "SINCERITY AUSTRALIA BUSINESS & MIGRATION PTY. LTD.",
    "ABN": "27139689786",
    "Address": {
      "Country": "Australia",
      "AddressLine1": "Level 9,",
      "AddressLine2": "167 Queen Street",
      "AddressLine3": null,
      "State": "VIC",
      "OtherState": null,
      "Suburb": "MELBOURNE",
      "OtherSuburb": null,
      "PostCode": "3000",
      "OtherPostCode": null,
      "Latitude": -37.8146236,
      "Longitude": 144.9604244,
      "FullAddress": "Level 9,\r\n167 Queen Street\r\nMELBOURNE VIC 3000\r\nAustralia"
    },
    "PostalAddress": {
      "Country": null,
      "AddressLine1": null,
      "AddressLine2": null,
      "AddressLine3": null,
      "State": null,
      "OtherState": null,
      "Suburb": "MELBOURNE",
      "OtherSuburb": null,
      "PostCode": null,
      "OtherPostCode": null,
      "Latitude": null,
      "Longitude": null,
      "FullAddress": "MELBOURNE"
    },
    "Contact": {
      "Phone": {
        "CountryCode": "61",
        "AreaCode": "1300",
        "Number": "737556",
        "FullNumber": "61 1300 737556"
      },
      "Phone2": {
        "CountryCode": null,
        "AreaCode": null,
        "Number": null,
        "FullNumber": null
      },
      "Phone3": {
        "CountryCode": null,
        "AreaCode": null,
        "Number": null,
        "FullNumber": null
      },
      "Fax": {
        "CountryCode": "61",
        "AreaCode": "3",
        "Number": "96428462",
        "FullNumber": "61 3 96428462"
      },
      "EmailAddress1": null,
      "EmailAddress2": null
    },
    "WebsiteUrl": null,
    "IsBusinessNameSameAsOwner": null,
    "IsBusinessNameRegistered": null,
    "HasHoldingCharge": null,
    "HasChangesInName": null,
    "ChangesInNameDetail": null,
    "ConnectedAgents": [],
    "HasEmployees": null,
    "HavingEmployeesDetail": null,
    "PrimaryContactId": null,
    "VerifiedDocuments": null,
    "OptionalDocuments": [],
    "OptionalExpiringDocuments": []
  },
  "Name": {
    "Salutation": "Mrs",
    "FirstName": "Tao",
    "SecondName": null,
    "FamilyName": "Jiang",
    "PostNominal": null,
    "FullName": "Mrs Tao Jiang",
    "GivenName": "Tao"
  },
  "MARN": "0854775",
  "IsNoFee": false,
  "ContactId": "5c28ebb9-a252-e311-9402-005056ab0eca",
  "CitizenshipCountries": [
    "Australia",
    "China"
  ],
  "OtherNames": [],
  "Aliases": [],
  "ApplicantReferenceID": null,
  "DisplayPublicationDate": "",
  "CurrentSanctionOutcome": null,
  "CurrentSanctionOutcome2": null,
  "SanctionedDate": null,
  "DisplaySanctionedDate": "",
  "DisplayCeasedDate": "01 Jan 0001"
}
