{
  "PrimaryBusiness": {
    "Relationship": "Owner",
    "IsPrimary": true,
    "IsExisting": false,
    "CID": "5952571616446",
    "CRN": "59525716164467",
    "IsProfileLockedOut": null,
    "BusinessId": "0a4ff515-7834-4c8f-b4e7-4f323b953834",
    "BusinessClassificationCode": "RMA",
    "BusinessClassification": "Registered Migration Agent",
    "BusinessType": "Sole Trader",
    "EntityName": "Eastwood Global Business and Migration Group",
    "Name": "Eastwood Global Business and Migration Group",
    "ABN": null,
    "Address": {
      "Country": "Hong Kong",
      "AddressLine1": "9 Consort Rise",
      "AddressLine2": null,
      "AddressLine3": null,
      "State": null,
      "OtherState": null,
      "Suburb": "Other",
      "OtherSuburb": "Pokfulam",
      "PostCode": "Other",
      "OtherPostCode": null,
      "Latitude": 7.06574010848999,
      "Longitude": 125.610778808594,
      "FullAddress": "9 Consort Rise\r\nPokfulam \r\nHong Kong"
    },
    "PostalAddress": {
      "Country": null,
      "AddressLine1": null,
      "AddressLine2": null,
      "AddressLine3": null,
      "State": null,
      "OtherState": null,
      "Suburb": null,
      "OtherSuburb": null,
      "PostCode": null,
      "OtherPostCode": null,
      "Latitude": null,
      "Longitude": null,
      "FullAddress": ""
    },
    "Contact": {
      "Phone": {
        "CountryCode": "852",
        "AreaCode": "00",
        "Number": "81910301",
        "FullNumber": "852 00 81910301"
      },
      "Phone2": {
        "CountryCode": null,
        "AreaCode": null,
        "Number": null,
        "FullNumber": null
      },
      "Phone3": {
        "CountryCode": null,
        "AreaCode": null,
        "Number": null,
        "FullNumber": null
      },
      "Fax": {
        "CountryCode": null,
        "AreaCode": null,
        "Number": null,
        "FullNumber": null
      },
      "EmailAddress1": null,
      "EmailAddress2": null
    },
    "WebsiteUrl": null,
    "IsBusinessNameSameAsOwner": null,
    "IsBusinessNameRegistered": null,
    "HasHoldingCharge": null,
    "HasChangesInName": null,
    "ChangesInNameDetail": null,
    "ConnectedAgents": [],
    "HasEmployees": null,
    "HavingEmployeesDetail": null,
    "PrimaryContactId": null,
    "VerifiedDocuments": null,
    "OptionalDocuments": [],
    "OptionalExpiringDocuments": []
  },
  "SecondaryBusinesses": [
    {
      "Relationship": "Owner",
      "IsPrimary": false,
      "IsExisting": false,
      "CID": "9508047128631",
      "CRN": "95080471286315",
      "IsProfileLockedOut": null,
      "BusinessId": "86deee59-1fc6-44cc-913d-34ac0179e1a3",
      "BusinessClassificationCode": "RMA",
      "BusinessClassification": "Registered Migration Agent",
      "BusinessType": "Sole Trader",
      "EntityName": "International Business",
      "Name": "Eastwood Global Business & Migration Group",
      "ABN": null,
      "Address": {
        "Country": "China",
        "AddressLine1": "27/F, Savannah Court, Chun Fang Road ",
        "AddressLine2": "Lo Wu",
        "AddressLine3": null,
        "State": null,
        "OtherState": "Guangdong",
        "Suburb": "Other",
        "OtherSuburb": "Shenzhen",
        "PostCode": "Other",
        "OtherPostCode": null,
        "Latitude": 22.5562191009521,
        "Longitude": 114.118789672852,
        "FullAddress": "27/F, Savannah Court, Chun Fang Road \r\nLo Wu\r\nShenzhen \r\nChina"
      },
      "PostalAddress": {
        "Country": null,
        "AddressLine1": null,
        "AddressLine2": null,
        "AddressLine3": null,
        "State": null,
        "OtherState": null,
        "Suburb": null,
        "OtherSuburb": null,
        "PostCode": null,
        "OtherPostCode": null,
        "Latitude": null,
        "Longitude": null,
        "FullAddress": ""
      },
      "Contact": {
        "Phone": {
          "CountryCode": "852",
          "AreaCode": "00",
          "Number": "81910301",
          "FullNumber": "852 00 81910301"
        },
        "Phone2": {
          "CountryCode": null,
          "AreaCode": null,
          "Number": null,
          "FullNumber": null
        },
        "Phone3": {
          "CountryCode": null,
          "AreaCode": null,
          "Number": null,
          "FullNumber": null
        },
        "Fax": {
          "CountryCode": null,
          "AreaCode": null,
          "Number": null,
          "FullNumber": null
        },
        "EmailAddress1": null,
        "EmailAddress2": null
      },
      "WebsiteUrl": null,
      "IsBusinessNameSameAsOwner": null,
      "IsBusinessNameRegistered": null,
      "HasHoldingCharge": null,
      "HasChangesInName": null,
      "ChangesInNameDetail": null,
      "ConnectedAgents": [],
      "HasEmployees": null,
      "HavingEmployeesDetail": null,
      "PrimaryContactId": null,
      "VerifiedDocuments": null,
      "OptionalDocuments": [],
      "OptionalExpiringDocuments": []
    },
    {
      "Relationship": "Owner",
      "IsPrimary": false,
      "IsExisting": false,
      "CID": "9518783804766",
      "CRN": "95187838047669",
      "IsProfileLockedOut": null,
      "BusinessId": "0ee6d527-d37b-4409-8b71-1aae21938411",
      "BusinessClassificationCode": "RMA",
      "BusinessClassification": "Registered Migration Agent",
      "BusinessType": "Sole Trader",
      "EntityName": "International Business",
      "Name": "Eastwood Global Business & Migration Group",
      "ABN": null,
      "Address": {
        "Country": "China",
        "AddressLine1": "3/F, Unispace",
        "AddressLine2": "150 Liulin Road",
        "AddressLine3": null,
        "State": null,
        "OtherState": "Shanghai",
        "Suburb": "Other",
        "OtherSuburb": "Shanghai",
        "PostCode": "Other",
        "OtherPostCode": null,
        "Latitude": 31.2551593780518,
        "Longitude": 121.474700927734,
        "FullAddress": "3/F, Unispace\r\n150 Liulin Road\r\nShanghai \r\nChina"
      },
      "PostalAddress": {
        "Country": null,
        "AddressLine1": null,
        "AddressLine2": null,
        "AddressLine3": null,
        "State": null,
        "OtherState": null,
        "Suburb": null,
        "OtherSuburb": null,
        "PostCode": null,
        "OtherPostCode": null,
        "Latitude": null,
        "Longitude": null,
        "FullAddress": ""
      },
      "Contact": {
        "Phone": {
          "CountryCode": "852",
          "AreaCode": "00",
          "Number": "81910301",
          "FullNumber": "852 00 81910301"
        },
        "Phone2": {
          "CountryCode": null,
          "AreaCode": null,
          "Number": null,
          "FullNumber": null
        },
        "Phone3": {
          "CountryCode": null,
          "AreaCode": null,
          "Number": null,
          "FullNumber": null
        },
        "Fax": {
          "CountryCode": null,
          "AreaCode": null,
          "Number": null,
          "FullNumber": null
        },
        "EmailAddress1": null,
        "EmailAddress2": null
      },
      "WebsiteUrl": null,
      "IsBusinessNameSameAsOwner": null,
      "IsBusinessNameRegistered": null,
      "HasHoldingCharge": null,
      "HasChangesInName": null,
      "ChangesInNameDetail": null,
      "ConnectedAgents": [],
      "HasEmployees": null,
      "HavingEmployeesDetail": null,
      "PrimaryContactId": null,
      "VerifiedDocuments": null,
      "OptionalDocuments": [],
      "OptionalExpiringDocuments": []
    },
    {
      "Relationship": "Owner",
      "IsPrimary": false,
      "IsExisting": false,
      "CID": "3391247213436",
      "CRN": "33912472134366",
      "IsProfileLockedOut": null,
      "BusinessId": "3d319481-5bc5-4f5c-96e4-157b888cfc2c",
      "BusinessClassificationCode": "RMA",
      "BusinessClassification": "Registered Migration Agent",
      "BusinessType": "Sole Trader",
      "EntityName": "International Business",
      "Name": "Eastwood Global Business and Migration Group",
      "ABN": null,
      "Address": {
        "Country": "China",
        "AddressLine1": "56/F, Guangzhou International Finance Centre",
        "AddressLine2": "Tin He",
        "AddressLine3": null,
        "State": null,
        "OtherState": null,
        "Suburb": "Other",
        "OtherSuburb": "Guangzhou",
        "PostCode": "Other",
        "OtherPostCode": null,
        "Latitude": 22.5562191009521,
        "Longitude": 114.118789672852,
        "FullAddress": "56/F, Guangzhou International Finance Centre\r\nTin He\r\nGuangzhou \r\nChina"
      },
      "PostalAddress": {
        "Country": null,
        "AddressLine1": null,
        "AddressLine2": null,
        "AddressLine3": null,
        "State": null,
        "OtherState": null,
        "Suburb": null,
        "OtherSuburb": null,
        "PostCode": null,
        "OtherPostCode": null,
        "Latitude": null,
        "Longitude": null,
        "FullAddress": ""
      },
      "Contact": {
        "Phone": {
          "CountryCode": "852",
          "AreaCode": "00",
          "Number": "81910301",
          "FullNumber": "852 00 81910301"
        },
        "Phone2": {
          "CountryCode": null,
          "AreaCode": null,
          "Number": null,
          "FullNumber": null
        },
        "Phone3": {
          "CountryCode": null,
          "AreaCode": null,
          "Number": null,
          "FullNumber": null
        },
        "Fax": {
          "CountryCode": null,
          "AreaCode": null,
          "Number": null,
          "FullNumber": null
        },
        "EmailAddress1": null,
        "EmailAddress2": null
      },
      "WebsiteUrl": null,
      "IsBusinessNameSameAsOwner": null,
      "IsBusinessNameRegistered": null,
      "HasHoldingCharge": null,
      "HasChangesInName": null,
      "ChangesInNameDetail": null,
      "ConnectedAgents": [],
      "HasEmployees": null,
      "HavingEmployeesDetail": null,
      "PrimaryContactId": null,
      "VerifiedDocuments": null,
      "OptionalDocuments": [],
      "OptionalExpiringDocuments": []
    },
    {
      "Relationship": "Owner",
      "IsPrimary": false,
      "IsExisting": false,
      "CID": "9513854761957",
      "CRN": "95138547619572",
      "IsProfileLockedOut": null,
      "BusinessId": "c7c25d3b-1aca-4995-9ab5-d0823639b642",
      "BusinessClassificationCode": "RMA",
      "BusinessClassification": "Registered Migration Agent",
      "BusinessType": "Sole Trader",
      "EntityName": "International Business",
      "Name": "Eastwood Global Business & Migration Group",
      "ABN": null,
      "Address": {
        "Country": "China",
        "AddressLine1": "10/F, Shui Tat Building",
        "AddressLine2": "74 Lu Coo Road",
        "AddressLine3": null,
        "State": null,
        "OtherState": "Beijing",
        "Suburb": "Other",
        "OtherSuburb": "Beijing",
        "PostCode": "Other",
        "OtherPostCode": null,
        "Latitude": 39.9065704345703,
        "Longitude": 116.387649536133,
        "FullAddress": "10/F, Shui Tat Building\r\n74 Lu Coo Road\r\nBeijing \r\nChina"
      },
      "PostalAddress": {
        "Country": null,
        "AddressLine1": null,
        "AddressLine2": null,
        "AddressLine3": null,
        "State": null,
        "OtherState": null,
        "Suburb": null,
        "OtherSuburb": null,
        "PostCode": null,
        "OtherPostCode": null,
        "Latitude": null,
        "Longitude": null,
        "FullAddress": ""
      },
      "Contact": {
        "Phone": {
          "CountryCode": "852",
          "AreaCode": "00",
          "Number": "81910301",
          "FullNumber": "852 00 81910301"
        },
        "Phone2": {
          "CountryCode": null,
          "AreaCode": null,
          "Number": null,
          "FullNumber": null
        },
        "Phone3": {
          "CountryCode": null,
          "AreaCode": null,
          "Number": null,
          "FullNumber": null
        },
        "Fax": {
          "CountryCode": null,
          "AreaCode": null,
          "Number": null,
          "FullNumber": null
        },
        "EmailAddress1": null,
        "EmailAddress2": null
      },
      "WebsiteUrl": null,
      "IsBusinessNameSameAsOwner": null,
      "IsBusinessNameRegistered": null,
      "HasHoldingCharge": null,
      "HasChangesInName": null,
      "ChangesInNameDetail": null,
      "ConnectedAgents": [],
      "HasEmployees": null,
      "HavingEmployeesDetail": null,
      "PrimaryContactId": null,
      "VerifiedDocuments": null,
      "OptionalDocuments": [],
      "OptionalExpiringDocuments": []
    }
  ],
  "DisplayBusiness": {
    "Relationship": "Owner",
    "IsPrimary": true,
    "IsExisting": false,
    "CID": "5952571616446",
    "CRN": "59525716164467",
    "IsProfileLockedOut": null,
    "BusinessId": "0a4ff515-7834-4c8f-b4e7-4f323b953834",
    "BusinessClassificationCode": "RMA",
    "BusinessClassification": "Registered Migration Agent",
    "BusinessType": "Sole Trader",
    "EntityName": "Eastwood Global Business and Migration Group",
    "Name": "Eastwood Global Business and Migration Group",
    "ABN": null,
    "Address": {
      "Country": "Hong Kong",
      "AddressLine1": "9 Consort Rise",
      "AddressLine2": null,
      "AddressLine3": null,
      "State": null,
      "OtherState": null,
      "Suburb": "Other",
      "OtherSuburb": "Pokfulam",
      "PostCode": "Other",
      "OtherPostCode": null,
      "Latitude": 7.06574010848999,
      "Longitude": 125.610778808594,
      "FullAddress": "9 Consort Rise\r\nPokfulam \r\nHong Kong"
    },
    "PostalAddress": {
      "Country": null,
      "AddressLine1": null,
      "AddressLine2": null,
      "AddressLine3": null,
      "State": null,
      "OtherState": null,
      "Suburb": null,
      "OtherSuburb": null,
      "PostCode": null,
      "OtherPostCode": null,
      "Latitude": null,
      "Longitude": null,
      "FullAddress": ""
    },
    "Contact": {
      "Phone": {
        "CountryCode": "852",
        "AreaCode": "00",
        "Number": "81910301",
        "FullNumber": "852 00 81910301"
      },
      "Phone2": {
        "CountryCode": null,
        "AreaCode": null,
        "Number": null,
        "FullNumber": null
      },
      "Phone3": {
        "CountryCode": null,
        "AreaCode": null,
        "Number": null,
        "FullNumber": null
      },
      "Fax": {
        "CountryCode": null,
        "AreaCode": null,
        "Number": null,
        "FullNumber": null
      },
      "EmailAddress1": null,
      "EmailAddress2": null
    },
    "WebsiteUrl": null,
    "IsBusinessNameSameAsOwner": null,
    "IsBusinessNameRegistered": null,
    "HasHoldingCharge": null,
    "HasChangesInName": null,
    "ChangesInNameDetail": null,
    "ConnectedAgents": [],
    "HasEmployees": null,
    "HavingEmployeesDetail": null,
    "PrimaryContactId": null,
    "VerifiedDocuments": null,
    "OptionalDocuments": [],
    "OptionalExpiringDocuments": []
  },
  "Name": {
    "Salutation": "Mr",
    "FirstName": "Yin Sang",
    "SecondName": null,
    "FamilyName": "Chan",
    "PostNominal": null,
    "FullName": "Mr Yin Sang Chan",
    "GivenName": "Yin Sang"
  },
  "MARN": "1679654",
  "IsNoFee": false,
  "ContactId": "b840c6bb-f18c-e511-9403-005056ab0eca",
  "CitizenshipCountries": [
    "Australia"
  ],
  "OtherNames": [],
  "Aliases": [],
  "ApplicantReferenceID": null,
  "DisplayPublicationDate": "",
  "CurrentSanctionOutcome": null,
  "CurrentSanctionOutcome2": null,
  "SanctionedDate": null,
  "DisplaySanctionedDate": "",
  "DisplayCeasedDate": "01 Jan 0001"
}
