{
  "PrimaryBusiness": {
    "Relationship": "Owner",
    "IsPrimary": true,
    "IsExisting": false,
    "CID": "0373156961048",
    "CRN": "03731569610484",
    "IsProfileLockedOut": null,
    "BusinessId": "c1dc86b3-3bbc-4cc6-86eb-856909f13879",
    "BusinessClassificationCode": "RMA",
    "BusinessClassification": "Registered Migration Agent",
    "BusinessType": "Sole Trader",
    "EntityName": "SHARMA, RAMAN ",
    "Name": "SHARMA, RAMAN ",
    "ABN": "87330741964",
    "Address": {
      "Country": "Australia",
      "AddressLine1": "14 Johnson Street",
      "AddressLine2": null,
      "AddressLine3": null,
      "State": "VIC",
      "OtherState": null,
      "Suburb": "OAKLEIGH",
      "OtherSuburb": null,
      "PostCode": "3166",
      "OtherPostCode": null,
      "Latitude": -37.7004499,
      "Longitude": 145.01118,
      "FullAddress": "14 Johnson Street\r\nOAKLEIGH VIC 3166\r\nAustralia"
    },
    "PostalAddress": {
      "Country": null,
      "AddressLine1": null,
      "AddressLine2": null,
      "AddressLine3": null,
      "State": null,
      "OtherState": null,
      "Suburb": null,
      "OtherSuburb": null,
      "PostCode": null,
      "OtherPostCode": null,
      "Latitude": null,
      "Longitude": null,
      "FullAddress": ""
    },
    "Contact": {
      "Phone": {
        "CountryCode": "61",
        "AreaCode": "3",
        "Number": "94240451",
        "FullNumber": "61 3 94240451"
      },
      "Phone2": {
        "CountryCode": null,
        "AreaCode": null,
        "Number": null,
        "FullNumber": null
      },
      "Phone3": {
        "CountryCode": null,
        "AreaCode": null,
        "Number": null,
        "FullNumber": null
      },
      "Fax": {
        "CountryCode": null,
        "AreaCode": null,
        "Number": null,
        "FullNumber": null
      },
      "EmailAddress1": null,
      "EmailAddress2": null
    },
    "WebsiteUrl": null,
    "IsBusinessNameSameAsOwner": null,
    "IsBusinessNameRegistered": null,
    "HasHoldingCharge": null,
    "HasChangesInName": null,
    "ChangesInNameDetail": null,
    "ConnectedAgents": [],
    "HasEmployees": null,
    "HavingEmployeesDetail": null,
    "PrimaryContactId": null,
    "VerifiedDocuments": null,
    "OptionalDocuments": [],
    "OptionalExpiringDocuments": []
  },
  "SecondaryBusinesses": [],
  "DisplayBusiness": {
    "Relationship": "Owner",
    "IsPrimary": true,
    "IsExisting": false,
    "CID": "0373156961048",
    "CRN": "03731569610484",
    "IsProfileLockedOut": null,
    "BusinessId": "c1dc86b3-3bbc-4cc6-86eb-856909f13879",
    "BusinessClassificationCode": "RMA",
    "BusinessClassification": "Registered Migration Agent",
    "BusinessType": "Sole Trader",
    "EntityName": "SHARMA, RAMAN ",
    "Name": "SHARMA, RAMAN ",
    "ABN": "87330741964",
    "Address": {
      "Country": "Australia",
      "AddressLine1": "14 Johnson Street",
      "AddressLine2": null,
      "AddressLine3": null,
      "State": "VIC",
      "OtherState": null,
      "Suburb": "OAKLEIGH",
      "OtherSuburb": null,
      "PostCode": "3166",
      "OtherPostCode": null,
      "Latitude": -37.7004499,
      "Longitude": 145.01118,
      "FullAddress": "14 Johnson Street\r\nOAKLEIGH VIC 3166\r\nAustralia"
    },
    "PostalAddress": {
      "Country": null,
      "AddressLine1": null,
      "AddressLine2": null,
      "AddressLine3": null,
      "State": null,
      "OtherState": null,
      "Suburb": null,
      "OtherSuburb": null,
      "PostCode": null,
      "OtherPostCode": null,
      "Latitude": null,
      "Longitude": null,
      "FullAddress": ""
    },
    "Contact": {
      "Phone": {
        "CountryCode": "61",
        "AreaCode": "3",
        "Number": "94240451",
        "FullNumber": "61 3 94240451"
      },
      "Phone2": {
        "CountryCode": null,
        "AreaCode": null,
        "Number": null,
        "FullNumber": null
      },
      "Phone3": {
        "CountryCode": null,
        "AreaCode": null,
        "Number": null,
        "FullNumber": null
      },
      "Fax": {
        "CountryCode": null,
        "AreaCode": null,
        "Number": null,
        "FullNumber": null
      },
      "EmailAddress1": null,
      "EmailAddress2": null
    },
    "WebsiteUrl": null,
    "IsBusinessNameSameAsOwner": null,
    "IsBusinessNameRegistered": null,
    "HasHoldingCharge": null,
    "HasChangesInName": null,
    "ChangesInNameDetail": null,
    "ConnectedAgents": [],
    "HasEmployees": null,
    "HavingEmployeesDetail": null,
    "PrimaryContactId": null,
    "VerifiedDocuments": null,
    "OptionalDocuments": [],
    "OptionalExpiringDocuments": []
  },
  "Name": {
    "Salutation": "Mr",
    "FirstName": "Raman",
    "SecondName": null,
    "FamilyName": "Sharma",
    "PostNominal": null,
    "FullName": "Mr Raman Sharma",
    "GivenName": "Raman"
  },
  "MARN": "1685970",
  "IsNoFee": false,
  "ContactId": "b07728ec-68a4-e511-9403-005056ab0eca",
  "CitizenshipCountries": [
    "Australia"
  ],
  "OtherNames": [],
  "Aliases": [],
  "ApplicantReferenceID": null,
  "DisplayPublicationDate": "",
  "CurrentSanctionOutcome": null,
  "CurrentSanctionOutcome2": null,
  "SanctionedDate": null,
  "DisplaySanctionedDate": "",
  "DisplayCeasedDate": "01 Jan 0001"
}
