{
  "PrimaryBusiness": {
    "Relationship": "Owner",
    "IsPrimary": true,
    "IsExisting": false,
    "CID": "7044857716299",
    "CRN": "70448577162996",
    "IsProfileLockedOut": null,
    "BusinessId": "ebf46503-2c4b-40f8-bf4e-f809a4bb9208",
    "BusinessClassificationCode": "RMA",
    "BusinessClassification": "Registered Migration Agent",
    "BusinessType": "Sole Trader",
    "EntityName": "LEE, TEVIN J ",
    "Name": "LEE, TEVIN J ",
    "ABN": "42364717461",
    "Address": {
      "Country": "Australia",
      "AddressLine1": "29 Halpine Parade",
      "AddressLine2": null,
      "AddressLine3": null,
      "State": "QLD",
      "OtherState": null,
      "Suburb": "WARNER",
      "OtherSuburb": null,
      "PostCode": "4500",
      "OtherPostCode": null,
      "Latitude": -27.31054,
      "Longitude": 152.9559,
      "FullAddress": "29 Halpine Parade\r\nWARNER QLD 4500\r\nAustralia"
    },
    "PostalAddress": {
      "Country": null,
      "AddressLine1": null,
      "AddressLine2": null,
      "AddressLine3": null,
      "State": null,
      "OtherState": null,
      "Suburb": null,
      "OtherSuburb": null,
      "PostCode": null,
      "OtherPostCode": null,
      "Latitude": null,
      "Longitude": null,
      "FullAddress": ""
    },
    "Contact": {
      "Phone": {
        "CountryCode": "61",
        "AreaCode": "7",
        "Number": "34193580",
        "FullNumber": "61 7 34193580"
      },
      "Phone2": {
        "CountryCode": null,
        "AreaCode": null,
        "Number": null,
        "FullNumber": null
      },
      "Phone3": {
        "CountryCode": null,
        "AreaCode": null,
        "Number": null,
        "FullNumber": null
      },
      "Fax": {
        "CountryCode": null,
        "AreaCode": null,
        "Number": null,
        "FullNumber": null
      },
      "EmailAddress1": null,
      "EmailAddress2": null
    },
    "WebsiteUrl": null,
    "IsBusinessNameSameAsOwner": null,
    "IsBusinessNameRegistered": null,
    "HasHoldingCharge": null,
    "HasChangesInName": null,
    "ChangesInNameDetail": null,
    "ConnectedAgents": [],
    "HasEmployees": null,
    "HavingEmployeesDetail": null,
    "PrimaryContactId": null,
    "VerifiedDocuments": null,
    "OptionalDocuments": [],
    "OptionalExpiringDocuments": []
  },
  "SecondaryBusinesses": [
    {
      "Relationship": "Employee",
      "IsPrimary": false,
      "IsExisting": false,
      "CID": "7044870369321",
      "CRN": "70448703693215",
      "IsProfileLockedOut": null,
      "BusinessId": "90c3c42d-0dbd-4a42-b304-0814db28e13e",
      "BusinessClassificationCode": "RMA",
      "BusinessClassification": "Registered Migration Agent",
      "BusinessType": "Company",
      "EntityName": "YOUNG EDUCATION CENTRE (AUST) PTY. LTD.",
      "Name": "EDUYOUNG.COM",
      "ABN": "51095597096",
      "Address": {
        "Country": "Australia",
        "AddressLine1": "233 Albert Street",
        "AddressLine2": null,
        "AddressLine3": null,
        "State": "QLD",
        "OtherState": null,
        "Suburb": "BRISBANE CITY",
        "OtherSuburb": null,
        "PostCode": "4000",
        "OtherPostCode": null,
        "Latitude": -27.47023,
        "Longitude": 153.02594,
        "FullAddress": "233 Albert Street\r\nBRISBANE CITY QLD 4000\r\nAustralia"
      },
      "PostalAddress": {
        "Country": null,
        "AddressLine1": null,
        "AddressLine2": null,
        "AddressLine3": null,
        "State": null,
        "OtherState": null,
        "Suburb": null,
        "OtherSuburb": null,
        "PostCode": null,
        "OtherPostCode": null,
        "Latitude": null,
        "Longitude": null,
        "FullAddress": ""
      },
      "Contact": {
        "Phone": {
          "CountryCode": "61",
          "AreaCode": "7",
          "Number": "30127200",
          "FullNumber": "61 7 30127200"
        },
        "Phone2": {
          "CountryCode": null,
          "AreaCode": null,
          "Number": null,
          "FullNumber": null
        },
        "Phone3": {
          "CountryCode": null,
          "AreaCode": null,
          "Number": null,
          "FullNumber": null
        },
        "Fax": {
          "CountryCode": null,
          "AreaCode": null,
          "Number": null,
          "FullNumber": null
        },
        "EmailAddress1": null,
        "EmailAddress2": null
      },
      "WebsiteUrl": null,
      "IsBusinessNameSameAsOwner": null,
      "IsBusinessNameRegistered": null,
      "HasHoldingCharge": null,
      "HasChangesInName": null,
      "ChangesInNameDetail": null,
      "ConnectedAgents": [],
      "HasEmployees": null,
      "HavingEmployeesDetail": null,
      "PrimaryContactId": null,
      "VerifiedDocuments": null,
      "OptionalDocuments": [],
      "OptionalExpiringDocuments": []
    },
    {
      "Relationship": "Independent Contractor",
      "IsPrimary": false,
      "IsExisting": false,
      "CID": "1567026244290",
      "CRN": "15670262442903",
      "IsProfileLockedOut": null,
      "BusinessId": "516b4021-6811-4308-ad8c-7adc59b769b9",
      "BusinessClassificationCode": "RMA",
      "BusinessClassification": "Registered Migration Agent",
      "BusinessType": "Company",
      "EntityName": "Y.A. CORPORATION AUSTRALIA PTY LTD",
      "Name": "Y.A. Education and Migration Services",
      "ABN": "56618034003",
      "Address": {
        "Country": "Australia",
        "AddressLine1": "Level 7",
        "AddressLine2": "127 Creek street",
        "AddressLine3": null,
        "State": "QLD",
        "OtherState": null,
        "Suburb": "BRISBANE CITY",
        "OtherSuburb": null,
        "PostCode": "4000",
        "OtherPostCode": null,
        "Latitude": -27.4657,
        "Longitude": 153.02774,
        "FullAddress": "Level 7\r\n127 Creek street\r\nBRISBANE CITY QLD 4000\r\nAustralia"
      },
      "PostalAddress": {
        "Country": null,
        "AddressLine1": null,
        "AddressLine2": null,
        "AddressLine3": null,
        "State": null,
        "OtherState": null,
        "Suburb": null,
        "OtherSuburb": null,
        "PostCode": null,
        "OtherPostCode": null,
        "Latitude": null,
        "Longitude": null,
        "FullAddress": ""
      },
      "Contact": {
        "Phone": {
          "CountryCode": "61",
          "AreaCode": "7",
          "Number": "32181216",
          "FullNumber": "61 7 32181216"
        },
        "Phone2": {
          "CountryCode": null,
          "AreaCode": null,
          "Number": null,
          "FullNumber": null
        },
        "Phone3": {
          "CountryCode": null,
          "AreaCode": null,
          "Number": null,
          "FullNumber": null
        },
        "Fax": {
          "CountryCode": null,
          "AreaCode": null,
          "Number": null,
          "FullNumber": null
        },
        "EmailAddress1": null,
        "EmailAddress2": null
      },
      "WebsiteUrl": null,
      "IsBusinessNameSameAsOwner": null,
      "IsBusinessNameRegistered": null,
      "HasHoldingCharge": null,
      "HasChangesInName": null,
      "ChangesInNameDetail": null,
      "ConnectedAgents": [],
      "HasEmployees": null,
      "HavingEmployeesDetail": null,
      "PrimaryContactId": null,
      "VerifiedDocuments": null,
      "OptionalDocuments": [],
      "OptionalExpiringDocuments": []
    }
  ],
  "DisplayBusiness": {
    "Relationship": "Owner",
    "IsPrimary": true,
    "IsExisting": false,
    "CID": "7044857716299",
    "CRN": "70448577162996",
    "IsProfileLockedOut": null,
    "BusinessId": "ebf46503-2c4b-40f8-bf4e-f809a4bb9208",
    "BusinessClassificationCode": "RMA",
    "BusinessClassification": "Registered Migration Agent",
    "BusinessType": "Sole Trader",
    "EntityName": "LEE, TEVIN J ",
    "Name": "LEE, TEVIN J ",
    "ABN": "42364717461",
    "Address": {
      "Country": "Australia",
      "AddressLine1": "29 Halpine Parade",
      "AddressLine2": null,
      "AddressLine3": null,
      "State": "QLD",
      "OtherState": null,
      "Suburb": "WARNER",
      "OtherSuburb": null,
      "PostCode": "4500",
      "OtherPostCode": null,
      "Latitude": -27.31054,
      "Longitude": 152.9559,
      "FullAddress": "29 Halpine Parade\r\nWARNER QLD 4500\r\nAustralia"
    },
    "PostalAddress": {
      "Country": null,
      "AddressLine1": null,
      "AddressLine2": null,
      "AddressLine3": null,
      "State": null,
      "OtherState": null,
      "Suburb": null,
      "OtherSuburb": null,
      "PostCode": null,
      "OtherPostCode": null,
      "Latitude": null,
      "Longitude": null,
      "FullAddress": ""
    },
    "Contact": {
      "Phone": {
        "CountryCode": "61",
        "AreaCode": "7",
        "Number": "34193580",
        "FullNumber": "61 7 34193580"
      },
      "Phone2": {
        "CountryCode": null,
        "AreaCode": null,
        "Number": null,
        "FullNumber": null
      },
      "Phone3": {
        "CountryCode": null,
        "AreaCode": null,
        "Number": null,
        "FullNumber": null
      },
      "Fax": {
        "CountryCode": null,
        "AreaCode": null,
        "Number": null,
        "FullNumber": null
      },
      "EmailAddress1": null,
      "EmailAddress2": null
    },
    "WebsiteUrl": null,
    "IsBusinessNameSameAsOwner": null,
    "IsBusinessNameRegistered": null,
    "HasHoldingCharge": null,
    "HasChangesInName": null,
    "ChangesInNameDetail": null,
    "ConnectedAgents": [],
    "HasEmployees": null,
    "HavingEmployeesDetail": null,
    "PrimaryContactId": null,
    "VerifiedDocuments": null,
    "OptionalDocuments": [],
    "OptionalExpiringDocuments": []
  },
  "Name": {
    "Salutation": "Mr",
    "FirstName": "Tevin",
    "SecondName": "Yj",
    "FamilyName": "Lee",
    "PostNominal": null,
    "FullName": "Mr Tevin Yj Lee",
    "GivenName": "Tevin Yj"
  },
  "MARN": "1688735",
  "IsNoFee": false,
  "ContactId": "1852b618-159c-e611-9403-005056ab0eca",
  "CitizenshipCountries": [
    "Australia"
  ],
  "OtherNames": [
    {
      "Id": "526028ca-57a1-e611-9403-005056ab0eca",
      "Type": "Also Known As",
      "FamilyName": null,
      "FirstName": null,
      "SecondName": null,
      "Alias": "Yong Ju Lee",
      "GivenName": ""
    }
  ],
  "Aliases": [
    "Yong Ju Lee"
  ],
  "ApplicantReferenceID": null,
  "DisplayPublicationDate": "",
  "CurrentSanctionOutcome": null,
  "CurrentSanctionOutcome2": null,
  "SanctionedDate": null,
  "DisplaySanctionedDate": "",
  "DisplayCeasedDate": "01 Jan 0001"
}
