{
  "PrimaryBusiness": {
    "Relationship": "Employee",
    "IsPrimary": true,
    "IsExisting": false,
    "CID": "6653672974436",
    "CRN": "66536729744364",
    "IsProfileLockedOut": null,
    "BusinessId": "0e24f5ec-9552-e311-9402-005056ab0eca",
    "BusinessClassificationCode": "RMA",
    "BusinessClassification": "Registered Migration Agent",
    "BusinessType": "Company",
    "EntityName": "ABK Group Pty Ltd",
    "Name": "ABK Group Pty Ltd",
    "ABN": "088 786 332",
    "Address": {
      "Country": "Australia",
      "AddressLine1": "12 Commercial Rd",
      "AddressLine2": null,
      "AddressLine3": null,
      "State": "VIC",
      "OtherState": null,
      "Suburb": "MENTONE",
      "OtherSuburb": null,
      "PostCode": "3194",
      "OtherPostCode": null,
      "Latitude": -37.9855719,
      "Longitude": 145.0663239,
      "FullAddress": "12 Commercial Rd\r\nMENTONE VIC 3194\r\nAustralia"
    },
    "PostalAddress": {
      "Country": null,
      "AddressLine1": null,
      "AddressLine2": null,
      "AddressLine3": null,
      "State": null,
      "OtherState": null,
      "Suburb": "MENTONE",
      "OtherSuburb": null,
      "PostCode": null,
      "OtherPostCode": null,
      "Latitude": null,
      "Longitude": null,
      "FullAddress": "MENTONE"
    },
    "Contact": {
      "Phone": {
        "CountryCode": "61",
        "AreaCode": "4",
        "Number": "14856168",
        "FullNumber": "61 4 14856168"
      },
      "Phone2": {
        "CountryCode": null,
        "AreaCode": null,
        "Number": null,
        "FullNumber": null
      },
      "Phone3": {
        "CountryCode": null,
        "AreaCode": null,
        "Number": null,
        "FullNumber": null
      },
      "Fax": {
        "CountryCode": null,
        "AreaCode": null,
        "Number": null,
        "FullNumber": null
      },
      "EmailAddress1": null,
      "EmailAddress2": null
    },
    "WebsiteUrl": null,
    "IsBusinessNameSameAsOwner": null,
    "IsBusinessNameRegistered": null,
    "HasHoldingCharge": null,
    "HasChangesInName": null,
    "ChangesInNameDetail": null,
    "ConnectedAgents": [],
    "HasEmployees": null,
    "HavingEmployeesDetail": null,
    "PrimaryContactId": null,
    "VerifiedDocuments": null,
    "OptionalDocuments": [],
    "OptionalExpiringDocuments": []
  },
  "SecondaryBusinesses": [],
  "DisplayBusiness": {
    "Relationship": "Employee",
    "IsPrimary": true,
    "IsExisting": false,
    "CID": "6653672974436",
    "CRN": "66536729744364",
    "IsProfileLockedOut": null,
    "BusinessId": "0e24f5ec-9552-e311-9402-005056ab0eca",
    "BusinessClassificationCode": "RMA",
    "BusinessClassification": "Registered Migration Agent",
    "BusinessType": "Company",
    "EntityName": "ABK Group Pty Ltd",
    "Name": "ABK Group Pty Ltd",
    "ABN": "088 786 332",
    "Address": {
      "Country": "Australia",
      "AddressLine1": "12 Commercial Rd",
      "AddressLine2": null,
      "AddressLine3": null,
      "State": "VIC",
      "OtherState": null,
      "Suburb": "MENTONE",
      "OtherSuburb": null,
      "PostCode": "3194",
      "OtherPostCode": null,
      "Latitude": -37.9855719,
      "Longitude": 145.0663239,
      "FullAddress": "12 Commercial Rd\r\nMENTONE VIC 3194\r\nAustralia"
    },
    "PostalAddress": {
      "Country": null,
      "AddressLine1": null,
      "AddressLine2": null,
      "AddressLine3": null,
      "State": null,
      "OtherState": null,
      "Suburb": "MENTONE",
      "OtherSuburb": null,
      "PostCode": null,
      "OtherPostCode": null,
      "Latitude": null,
      "Longitude": null,
      "FullAddress": "MENTONE"
    },
    "Contact": {
      "Phone": {
        "CountryCode": "61",
        "AreaCode": "4",
        "Number": "14856168",
        "FullNumber": "61 4 14856168"
      },
      "Phone2": {
        "CountryCode": null,
        "AreaCode": null,
        "Number": null,
        "FullNumber": null
      },
      "Phone3": {
        "CountryCode": null,
        "AreaCode": null,
        "Number": null,
        "FullNumber": null
      },
      "Fax": {
        "CountryCode": null,
        "AreaCode": null,
        "Number": null,
        "FullNumber": null
      },
      "EmailAddress1": null,
      "EmailAddress2": null
    },
    "WebsiteUrl": null,
    "IsBusinessNameSameAsOwner": null,
    "IsBusinessNameRegistered": null,
    "HasHoldingCharge": null,
    "HasChangesInName": null,
    "ChangesInNameDetail": null,
    "ConnectedAgents": [],
    "HasEmployees": null,
    "HavingEmployeesDetail": null,
    "PrimaryContactId": null,
    "VerifiedDocuments": null,
    "OptionalDocuments": [],
    "OptionalExpiringDocuments": []
  },
  "Name": {
    "Salutation": "Ms",
    "FirstName": "Beth",
    "SecondName": null,
    "FamilyName": "Kennedy",
    "PostNominal": null,
    "FullName": "Ms Beth Kennedy",
    "GivenName": "Beth"
  },
  "MARN": "9685250",
  "IsNoFee": false,
  "ContactId": "7cd3ef20-a652-e311-9402-005056ab0eca",
  "CitizenshipCountries": [
    "Australia"
  ],
  "OtherNames": [
    {
      "Id": "02077300-0453-e311-9402-005056ab0eca",
      "Type": "Former Name",
      "FamilyName": "McGechie",
      "FirstName": "Beth",
      "SecondName": null,
      "Alias": null,
      "GivenName": "Beth"
    }
  ],
  "Aliases": [],
  "ApplicantReferenceID": null,
  "DisplayPublicationDate": "",
  "CurrentSanctionOutcome": null,
  "CurrentSanctionOutcome2": null,
  "SanctionedDate": null,
  "DisplaySanctionedDate": "",
  "DisplayCeasedDate": "01 Jan 0001"
}
