{"preqs":"Admission to Masters of Architecture or by permission, OHS1000","creditPoints":6,"rules":[{"startDate":"1/10/2010","status":"ACTIVE","ruleSummary":"COREQ","ruleString":"Must be enrolled in course version {3120}","endDate":"31/12/2015"},{"startDate":"1/01/2016","status":"ACTIVE","ruleSummary":"COREQ","ruleString":"Must be enrolled in course version {3120, F6001}","endDate":""},{"startDate":"1/10/2010","status":"ACTIVE","ruleSummary":"PREREQ-IW","ruleString":"Must have passed 1 (I/W) units in {OHS1000}","endDate":"31/12/2015"},{"startDate":"1/01/2016","status":"ACTIVE","ruleSummary":"PREREQ-IW","ruleString":"Must have passed 1 (I/W) units in {OHS1000}","endDate":""}],"locationAndTime":[{"location":"Caulfield","time":["Second semester 2017 (Day)","Second semester 2017 (Evening)","Trimester 2 2017 (Off-campus block of classes)"]},{"location":"Prato","time":["Trimester 2 2017 (Off-campus block of classes)"]}],"enjoyScore":3.25,"learnScore":3.444444444,"learnResponse":7,"proh":"","scaBand":2,"unitName":"Advanced Studies in Architecture 4","description":"This unit explores aspects of architectural media. This unit examines a range of discursive and material aspects of architectural media. It will take into consideration various cultural, social, and technological factors utilizing historical, theoretical, and projective approaches. Investigations will incorporate various methodologies and diverse points of view with an underlying concern for the implications for architectural design. The unit will foster skills necessary for assessing and contributing to the built environment.","enjoyResponse":7,"faculty":"Faculty of Art, Design and Architecture","unitCode":"ARC5502","eftsl":0.125}