{"preqs":"","creditPoints":6,"rules":[{"startDate":"1/01/2016","status":"ACTIVE","ruleSummary":"COREQ","ruleString":"Must be enrolled in course type {10, 20, 41, 50}","endDate":""},{"startDate":"1/01/2016","status":"ACTIVE","ruleSummary":"TRANS","ruleString":"Unit was previously coded {3100, DEK112, DEK1120%, GBU1401%, GSM2200, GSM3210, MGC2200, MKB1401%, MKB1600, MKC1200, MKC2200, MKF1120%, MKG1401%, MKP1120, MKS1120, MKT112, MKT1120%, MKW1120%, MKX1120%}","endDate":""},{"startDate":"1/01/2016","status":"ACTIVE","ruleSummary":"INCOMP-IW","ruleString":"Incompatible with achievement in (I/W) {MKB1200, MKC1200, MKF1120, MKG1120, MKP1120, MKW1120}","endDate":""}],"locationAndTime":[{"location":"South Africa","time":["Second semester 2017 (Day)","Summer semester B (starts January) 2017 (On-campus block of classes)"]}],"enjoyScore":3.96875,"learnScore":4.304563492,"learnResponse":19,"proh":"MKB1200, MKC1200, MKF1120, MKG1120, MKP1120, MKW1120.","scaBand":3,"unitName":"Marketing theory and practice","description":"This unit provides an introduction to marketing activities undertaken by business, government, profit and non profit organisations. It explores marketing theory, the marketing concept and its evolution from a strategic and applied perspective, development of corporate and marketing strategic plans, analysis of an organisation and marketing\u0027s role, value-exchange processes, buyer behaviour, marketing research and market analysis, the marketing environment, the use of marketing decision making tools, product concepts, strategies and development, distribution, pricing and communication mix strategies, services marketing, marketing management, and implementation and control processes and procedures.","enjoyResponse":64,"faculty":"Faculty of Business and Economics","unitCode":"MKS1120","eftsl":0.125}