{"preqs":"Completion of first year in any degree (48 points) at Monash University.","creditPoints":6,"rules":[{"startDate":"1/01/2009","status":"ACTIVE","ruleSummary":"PREREQ-IW","ruleString":"Must have passed 48 (I/W) credit points at levels {1, 2, 3}","endDate":""}],"locationAndTime":[{"location":"Not Offered in 2017","time":[]}],"enjoyScore":3,"learnScore":3,"learnResponse":0,"proh":"","scaBand":1,"unitName":"Positive psychology","description":"Positive psychology focuses on promoting optimal human functioning. Theoretical perspectives will be examined to demonstrate the impact of positive conditions in achieving desirable outcomes. Information concerning the latest evidence-based interventions about what makes people happy and how happiness is defined and measured will be presented.  The relevance of positive psychology in a range of contexts and across the life span will be explored. Numerous and varied learning approaches such as debates, case studies, role plays, watching videos, keeping journals and research activities will be undertaken. This unit will be based on evidence-based knowledge and practice and will also involve an experiential component to facilitate learning.","enjoyResponse":0,"faculty":"Faculty of Medicine, Nursing and Health Sciences","unitCode":"PSY3250","eftsl":0.125}